Metadata-Version: 2.1
Name: py-pkg-tmpl
Version: 0.0.1.dev0
Summary: Template for creating and generic Python packages
Author: Sabar Dasgupta
Author-email: s@bardasgupta.com
License: AGPLv3
Requires-Python: >=3.7
License-File: LICENSE
